[
  {
    "name": "Hospital Management System",
    "description": "A full-featured Hospital management system with payment integration, user authentication, admin and user dashboard.",
    "status": "In Progress",
    "technologies": "React, Express, MongoDB, Stripe, REST API, Passport",
    "repo": "https://github.com/ahsan2014s/Hospital-Management"
  },
  {
    "name": "Spiking Neural Network Optimization",
    "description": "Spiking Neural network resembles how our neural network processes data. We are implementing some optimizations.",
    "status": "In Progress",
    "technologies": "Python, TensorFlow, Scikit, NLP",
    "repo": "https://github.com/ahsan2014s/snn-optimization"
  },
  {
    "name": "Large Dataset for Bangla",
    "description": "A very large dataset for Bangla with emotion and tone classifiers.",
    "status": "Planned",
    "technologies": "CSV, Distillation",
    "repo": "https://github.com/ahsan2014s/bangla-dataset"
  }
]
